{
  "version": "5.2.1",
  "flags": {},
  "shapes": [
    {
      "label": "insect",
      "points": [
        [
          122.0,
          347.5
        ],
        [
          122.0,
          351.5
        ],
        [
          126.0,
          356.0
        ],
        [
          123.0,
          358.0
        ],
        [
          122.5,
          361.5
        ],
        [
          125.5,
          362.5
        ],
        [
          127.0,
          359.0
        ],
        [
          131.0,
          357.0
        ],
        [
          134.0,
          357.0
        ],
        [
          134.5,
          359.0
        ],
        [
          137.0,
          358.5
        ],
        [
          136.0,
          366.0
        ],
        [
          137.5,
          363.5
        ],
        [
          139.5,
          365.5
        ],
        [
          137.5,
          375.0
        ],
        [
          144.0,
          376.5
        ],
        [
          147.0,
          370.5
        ],
        [
          146.5,
          359.0
        ],
        [
          149.0,
          359.0
        ],
        [
          146.5,
          349.5
        ],
        [
          141.5,
          350.0
        ],
        [
          138.0,
          347.0
        ],
        [
          130.0,
          348.5
        ],
        [
          129.5,
          346.0
        ],
        [
          124.5,
          345.5
        ],
        [
          122.0,
          347.5
        ]
      ],
      "group_id": null,
      "shape_type": "polygon",
      "flags": {}
    },
    {
      "label": "insect",
      "points": [
        [
          566.5,
          141.0
        ],
        [
          558.0,
          145.5
        ],
        [
          550.5,
          153.5
        ],
        [
          549.0,
          158.5
        ],
        [
          552.0,
          164.0
        ],
        [
          548.5,
          168.5
        ],
        [
          543.5,
          172.0
        ],
        [
          532.5,
          184.5
        ],
        [
          526.5,
          187.0
        ],
        [
          527.5,
          189.0
        ],
        [
          535.0,
          188.0
        ],
        [
          535.5,
          185.0
        ],
        [
          547.5,
          175.0
        ],
        [
          560.0,
          169.5
        ],
        [
          570.5,
          169.0
        ],
        [
          576.0,
          166.57352941176487
        ],
        [
          576.0,
          138.57446808510622
        ],
        [
          566.5,
          141.0
        ]
      ],
      "group_id": null,
      "shape_type": "polygon",
      "flags": {}
    },
    {
      "label": "insect",
      "points": [
        [
          478.5,
          226.0
        ],
        [
          499.0,
          220.5
        ],
        [
          521.0,
          219.5
        ],
        [
          531.0,
          224.0
        ],
        [
          543.0,
          227.0
        ],
        [
          554.5,
          225.5
        ],
        [
          564.5,
          230.0
        ],
        [
          574.5,
          230.5
        ],
        [
          576.0,
          231.625
        ],
        [
          576.0,
          198.0
        ],
        [
          544.5,
          188.5
        ],
        [
          534.0,
          187.5
        ],
        [
          518.0,
          195.0
        ],
        [
          512.0,
          199.5
        ],
        [
          510.0,
          204.5
        ],
        [
          512.5,
          207.5
        ],
        [
          509.5,
          210.5
        ],
        [
          475.5,
          222.0
        ],
        [
          475.0,
          224.0
        ],
        [
          471.5,
          226.0
        ],
        [
          478.5,
          226.0
        ]
      ],
      "group_id": null,
      "shape_type": "polygon",
      "flags": {}
    },
    {
      "label": "insect",
      "points": [
        [
          564.5,
          251.0
        ],
        [
          559.0,
          266.0
        ],
        [
          558.0,
          275.0
        ],
        [
          563.0,
          271.0
        ],
        [
          565.5,
          263.5
        ],
        [
          576.0,
          255.82692307692287
        ],
        [
          576.0,
          241.71153846153857
        ],
        [
          564.5,
          251.0
        ]
      ],
      "group_id": null,
      "shape_type": "polygon",
      "flags": {}
    },
    {
      "label": "insect",
      "points": [
        [
          258.5,
          195.0
        ],
        [
          260.0,
          203.0
        ],
        [
          258.5,
          204.5
        ],
        [
          256.5,
          204.5
        ],
        [
          250.0,
          198.5
        ],
        [
          248.5,
          199.0
        ],
        [
          255.5,
          205.0
        ],
        [
          258.0,
          212.0
        ],
        [
          256.5,
          214.0
        ],
        [
          250.0,
          213.0
        ],
        [
          247.5,
          229.5
        ],
        [
          241.0,
          233.0
        ],
        [
          238.0,
          232.5
        ],
        [
          231.0,
          224.0
        ],
        [
          222.5,
          220.0
        ],
        [
          233.5,
          239.5
        ],
        [
          226.0,
          245.5
        ],
        [
          210.5,
          247.5
        ],
        [
          203.0,
          242.5
        ],
        [
          206.0,
          248.0
        ],
        [
          203.5,
          250.0
        ],
        [
          199.5,
          248.0
        ],
        [
          199.0,
          249.0
        ],
        [
          208.0,
          253.5
        ],
        [
          216.0,
          252.5
        ],
        [
          217.5,
          254.0
        ],
        [
          217.0,
          257.0
        ],
        [
          209.5,
          260.5
        ],
        [
          205.5,
          258.5
        ],
        [
          206.5,
          260.5
        ],
        [
          190.5,
          265.5
        ],
        [
          188.5,
          270.0
        ],
        [
          185.5,
          269.5
        ],
        [
          182.5,
          273.0
        ],
        [
          179.0,
          284.5
        ],
        [
          175.0,
          285.5
        ],
        [
          184.0,
          288.5
        ],
        [
          189.0,
          288.0
        ],
        [
          190.5,
          290.5
        ],
        [
          195.0,
          290.5
        ],
        [
          196.0,
          286.0
        ],
        [
          202.5,
          283.5
        ],
        [
          205.5,
          284.0
        ],
        [
          208.5,
          287.0
        ],
        [
          212.0,
          286.0
        ],
        [
          212.0,
          283.0
        ],
        [
          214.0,
          280.5
        ],
        [
          222.5,
          277.5
        ],
        [
          232.5,
          270.5
        ],
        [
          254.0,
          251.0
        ],
        [
          260.5,
          239.0
        ],
        [
          262.5,
          228.0
        ],
        [
          262.5,
          201.5
        ],
        [
          259.5,
          191.0
        ],
        [
          258.5,
          195.0
        ]
      ],
      "group_id": null,
      "shape_type": "polygon",
      "flags": {}
    },
    {
      "label": "insect",
      "points": [
        [
          179.5,
          253.5
        ],
        [
          177.0,
          250.5
        ],
        [
          158.0,
          251.0
        ],
        [
          152.0,
          249.5
        ],
        [
          145.0,
          244.5
        ],
        [
          144.5,
          238.5
        ],
        [
          136.0,
          238.5
        ],
        [
          135.0,
          243.0
        ],
        [
          130.0,
          246.5
        ],
        [
          128.5,
          250.0
        ],
        [
          117.5,
          258.0
        ],
        [
          114.5,
          265.0
        ],
        [
          108.5,
          270.0
        ],
        [
          106.0,
          274.5
        ],
        [
          100.0,
          301.5
        ],
        [
          94.5,
          311.0
        ],
        [
          94.5,
          316.0
        ],
        [
          92.0,
          322.0
        ],
        [
          89.0,
          325.5
        ],
        [
          89.5,
          330.5
        ],
        [
          76.5,
          378.0
        ],
        [
          78.5,
          383.5
        ],
        [
          82.5,
          387.5
        ],
        [
          82.5,
          396.0
        ],
        [
          78.0,
          410.5
        ],
        [
          78.5,
          415.5
        ],
        [
          73.0,
          427.5
        ],
        [
          69.27999999999997,
          430.8850000000002
        ],
        [
          63.335000000000036,
          436.83500000000004
        ],
        [
          63.5,
          442.0
        ],
        [
          54.700000000000045,
          455.5500000000002
        ],
        [
          61.0,
          449.0
        ],
        [
          72.0,
          435.5
        ],
        [
          75.0,
          435.5
        ],
        [
          78.0,
          439.5
        ],
        [
          77.20000000000005,
          457.4000000000001
        ],
        [
          93.0,
          391.5
        ],
        [
          95.5,
          388.0
        ],
        [
          109.5,
          379.5
        ],
        [
          120.5,
          362.0
        ],
        [
          125.0,
          362.0
        ],
        [
          128.0,
          357.5
        ],
        [
          134.0,
          353.0
        ],
        [
          134.0,
          347.5
        ],
        [
          130.0,
          344.5
        ],
        [
          130.0,
          337.5
        ],
        [
          136.0,
          325.5
        ],
        [
          139.0,
          323.0
        ],
        [
          159.0,
          338.5
        ],
        [
          164.5,
          338.0
        ],
        [
          182.0,
          347.5
        ],
        [
          184.0,
          347.5
        ],
        [
          184.5,
          346.0
        ],
        [
          178.0,
          338.5
        ],
        [
          178.0,
          334.5
        ],
        [
          181.0,
          331.0
        ],
        [
          217.0,
          339.5
        ],
        [
          214.5,
          336.5
        ],
        [
          202.5,
          331.5
        ],
        [
          185.0,
          326.5
        ],
        [
          173.5,
          316.0
        ],
        [
          149.5,
          302.0
        ],
        [
          147.0,
          298.5
        ],
        [
          148.5,
          292.5
        ],
        [
          154.5,
          289.5
        ],
        [
          159.0,
          290.0
        ],
        [
          161.5,
          294.5
        ],
        [
          169.5,
          294.0
        ],
        [
          176.0,
          289.0
        ],
        [
          183.5,
          279.5
        ],
        [
          187.0,
          281.5
        ],
        [
          191.5,
          297.5
        ],
        [
          192.5,
          308.5
        ],
        [
          198.0,
          320.5
        ],
        [
          199.0,
          316.5
        ],
        [
          196.5,
          305.5
        ],
        [
          195.5,
          288.5
        ],
        [
          199.0,
          285.0
        ],
        [
          199.0,
          281.0
        ],
        [
          206.0,
          284.5
        ],
        [
          215.0,
          292.5
        ],
        [
          217.5,
          292.5
        ],
        [
          214.5,
          287.0
        ],
        [
          215.5,
          281.0
        ],
        [
          202.0,
          265.0
        ],
        [
          179.5,
          253.5
        ]
      ],
      "group_id": null,
      "shape_type": "polygon",
      "flags": {}
    },
    {
      "label": "insect",
      "points": [
        [
          188.0,
          294.0
        ],
        [
          183.5,
          289.5
        ],
        [
          169.5,
          291.0
        ],
        [
          166.0,
          293.0
        ],
        [
          165.0,
          296.5
        ],
        [
          158.0,
          301.5
        ],
        [
          150.5,
          304.5
        ],
        [
          139.0,
          317.0
        ],
        [
          134.5,
          327.0
        ],
        [
          140.0,
          325.0
        ],
        [
          141.5,
          326.0
        ],
        [
          141.5,
          336.5
        ],
        [
          148.5,
          345.0
        ],
        [
          154.0,
          345.5
        ],
        [
          158.0,
          342.5
        ],
        [
          163.5,
          333.0
        ],
        [
          175.5,
          319.0
        ],
        [
          174.0,
          316.0
        ],
        [
          169.5,
          314.5
        ],
        [
          171.0,
          311.0
        ],
        [
          184.0,
          304.5
        ],
        [
          188.0,
          298.5
        ],
        [
          191.0,
          300.0
        ],
        [
          191.5,
          304.0
        ],
        [
          192.0,
          293.0
        ],
        [
          190.5,
          291.5
        ],
        [
          188.0,
          294.0
        ]
      ],
      "group_id": null,
      "shape_type": "polygon",
      "flags": {}
    },
    {
      "label": "insect",
      "points": [
        [
          6.5,
          150.0
        ],
        [
          6.0,
          147.5
        ],
        [
          0.0,
          146.0
        ],
        [
          0.0,
          149.1875
        ],
        [
          6.5,
          150.0
        ]
      ],
      "group_id": null,
      "shape_type": "polygon",
      "flags": {}
    },
    {
      "label": "insect",
      "points": [
        [
          302.5,
          568.0
        ],
        [
          304.5,
          569.5
        ],
        [
          304.5,
          572.5
        ],
        [
          308.5,
          575.0
        ],
        [
          308.3125,
          576.0
        ],
        [
          325.3103448275863,
          576.0
        ],
        [
          325.0,
          571.5
        ],
        [
          322.0,
          567.0
        ],
        [
          317.0,
          564.0
        ],
        [
          317.5,
          558.0
        ],
        [
          309.0,
          559.5
        ],
        [
          304.5,
          562.5
        ],
        [
          302.5,
          568.0
        ]
      ],
      "group_id": null,
      "shape_type": "polygon",
      "flags": {}
    },
    {
      "label": "insect",
      "points": [
        [
          337.26,
          564.8600000000001
        ],
        [
          336.145,
          570.4299999999998
        ],
        [
          335.8186500395884,
          576.0
        ],
        [
          351.7496888141295,
          576.0
        ],
        [
          351.3800000000001,
          573.0300000000002
        ],
        [
          351.3800000000001,
          567.0900000000001
        ],
        [
          353.605,
          561.145
        ],
        [
          353.605,
          554.8299999999999
        ],
        [
          349.8900000000001,
          550.0
        ],
        [
          343.95000000000005,
          549.2550000000001
        ],
        [
          338.0050000000001,
          558.915
        ],
        [
          337.26,
          564.8600000000001
        ]
      ],
      "group_id": null,
      "shape_type": "polygon",
      "flags": {}
    }
  ],
  "imagePath": "L2_ctrain13_1152_2880.jpg",
  "imageData": null,
  "imageHeight": 576,
  "imageWidth": 576
}